llm_mri/LLM_MRI.py
llm_mri/Treatment.py
llm_mri/__init__.py
llm_mri-0.1.10.dist-info/LICENSE.md
llm_mri-0.1.10.dist-info/METADATA
llm_mri-0.1.10.dist-info/WHEEL
llm_mri-0.1.10.dist-info/RECORD
