Metadata-Version: 2.1
Name: llm_mri
Version: 0.1.10
Summary: Package to visualize LLM's Neural Networks activation regions
Author: lipecorradini
Author-email: luizfelipecorradini@gmail.com
Requires-Python: >=3.10,<4.0
Classifier: Programming Language :: Python :: 3
Classifier: Programming Language :: Python :: 3.10
Classifier: Programming Language :: Python :: 3.11
Classifier: Programming Language :: Python :: 3.12
Requires-Dist: datasets (>=2.19.1,<3.0.0)
Requires-Dist: graphviz (>=0.20.3,<0.21.0)
Requires-Dist: ipykernel (>=6.29.5,<7.0.0)
Requires-Dist: matplotlib (>=3.9.0,<4.0.0)
Requires-Dist: networkx (>=3.3,<4.0)
Requires-Dist: numpy (>=1.26.4,<2.0.0)
Requires-Dist: pandas (>=2.2.2,<3.0.0)
Requires-Dist: progress (>=1.6,<2.0)
Requires-Dist: pydot (>=2.0.0,<3.0.0)
Requires-Dist: pygraphviz (>=1.13,<2.0)
Requires-Dist: pyqt6 (>=6.7.1,<7.0.0)
Requires-Dist: seaborn (>=0.13.2,<0.14.0)
Requires-Dist: sklearn-preprocessing (>=0.1.0,<0.2.0)
Requires-Dist: torch (>=2.3.1,<3.0.0)
Requires-Dist: transformers (>=4.41.0,<5.0.0)
Requires-Dist: umap-learn (>=0.5.6,<0.6.0)
